{
  "candidateId": "man-2703905980b557ba7cfb4fa9",
  "result": {
    "status": "passed",
    "evidence": {
      "candidateId": "man-2703905980b557ba7cfb4fa9",
      "candidateRevision": 0,
      "candidateContentHash": "bb3087b964ce8ba9efa6dda269eef924a79d2a6f9422f2a8890c8f384a55180d",
      "blueprintHash": "49d8844d339eb38046c7e8694e79b8a75c5eb54c7b53fb95c9ecd5f7d226b877",
      "validatorVersion": "1",
      "schemaVersion": "1",
      "taxonomyVersion": "1",
      "validatedAt": "2026-07-23T14:54:45.258Z",
      "checksPerformed": [
        "candidate_identity",
        "provenance_binding",
        "lifecycle_state",
        "donor_trust_fields",
        "source_path",
        "taxonomy",
        "registry_membership",
        "production_schema",
        "content_safety",
        "scoring_compatibility"
      ],
      "issueSummary": {
        "errorCount": 0,
        "codes": []
      },
      "outcome": "passed",
      "validationFingerprint": "f2e1c774af7e5545d2304b64bb2d963f417f28870b90844427da5b0a5074ab61"
    }
  }
}