{
  "candidateId": "man-480083ddbce11a48d525ee44",
  "result": {
    "status": "passed",
    "evidence": {
      "candidateId": "man-480083ddbce11a48d525ee44",
      "candidateRevision": 0,
      "candidateContentHash": "35fdccfa936534ef7afaf727ce2a23a88c9baf625226571f4b4712f0f6c5ac9a",
      "blueprintHash": "93e1dece74de31bd7a5bfbe50e5450a905c33cb61ab5e0e0f5609b33ee892e42",
      "validatorVersion": "1",
      "schemaVersion": "1",
      "taxonomyVersion": "1",
      "validatedAt": "2026-07-23T13:37:11.914Z",
      "checksPerformed": [
        "candidate_identity",
        "provenance_binding",
        "lifecycle_state",
        "donor_trust_fields",
        "source_path",
        "taxonomy",
        "registry_membership",
        "production_schema",
        "content_safety",
        "scoring_compatibility"
      ],
      "issueSummary": {
        "errorCount": 0,
        "codes": []
      },
      "outcome": "passed",
      "validationFingerprint": "78dcee471f862198330cc600258e5ceb5f63cf958053ee175b1852156290cd4b"
    }
  }
}